autospares/__init__.py
autospares/lala.py
autospares/models.py
autospares-0.0.7.dist-info/LICENSE
autospares-0.0.7.dist-info/METADATA
autospares-0.0.7.dist-info/WHEEL
autospares-0.0.7.dist-info/top_level.txt
autospares-0.0.7.dist-info/RECORD
