Metadata-Version: 2.1
Name: autospares
Version: 0.0.7
Summary: short package description
Home-page: https://www.freecodecamp.org/news/how-to-create-and-upload-your-first-python-package-to-pypi/
Author: adrian_k
Author-email: author@example.com
Project-URL: Bug Tracker, https://www.freecodecamp.org/news/how-to-create-and-upload-your-first-python-package-to-pypi/
Classifier: Programming Language :: Python :: 3
Classifier: License :: OSI Approved :: MIT License
Classifier: Operating System :: OS Independent
Requires-Python: >=3.6
License-File: LICENSE
